{
    "Ax": {
        "error": 1.7349535090777623e-07,
        "error_type": "SEM",
        "filter_outliers_dict": {
            "filter_outliers": false,
            "iterations": 1,
            "std_devs": 2
        },
        "fit": "average",
        "value": -7.22549831994564e-07
    },
    "H2": {
        "error": 1.0601363360959947e-07,
        "error_type": "SEM",
        "filter_outliers_dict": {
            "filter_outliers": true,
            "iterations": 1,
            "std_devs": 2
        },
        "fit": "average",
        "value": -7.534977714009188e-07
    },
    "H4": {
        "error": 8.889891403827077e-08,
        "error_type": "SEM",
        "filter_outliers_dict": {
            "filter_outliers": true,
            "iterations": 1,
            "std_devs": 2
        },
        "fit": "average",
        "value": -6.057519328071429e-07
    },
    "L2": {
        "error": 1.447967528928917e-07,
        "error_type": "SEM",
        "filter_outliers_dict": {
            "filter_outliers": true,
            "iterations": 1,
            "std_devs": 2
        },
        "fit": "average",
        "value": -4.5403943601704756e-08
    },
    "L4": {
        "error": 1.107273064716533e-09,
        "error_type": "SEM",
        "filter_outliers_dict": {
            "filter_outliers": false,
            "iterations": 1,
            "std_devs": 2
        },
        "fit": "average",
        "value": 2.6666666666666666e-09
    }
}